CHANGES.txt
LICENSE.txt
MANIFEST.in
PackageInfo.cfg
README.rst
README.txt
_dist_
_dist_local_
html
setup.cfg
setup.py
docsrc/Makefile
docsrc/conf.py
docsrc/index.rst
examples/barbecue/CHANGES.txt
examples/barbecue/LICENSE.txt
examples/barbecue/MANIFEST.in
examples/barbecue/README.rst
examples/barbecue/setup.py
examples/barbecue/barbecue/__init__.py
examples/barbecue/barbecue/_barbecue.py
examples/barbecue/barbecue/schema/barbecue-time.yml
examples/barbecue/bin/barbecue-time
examples/barbecue/dist/barbecue-0.1b1.tar.gz
examples/barbecue/dist/barbecue-0.1b1/CHANGES.txt
examples/barbecue/dist/barbecue-0.1b1/LICENSE.txt
examples/barbecue/dist/barbecue-0.1b1/MANIFEST.in
examples/barbecue/dist/barbecue-0.1b1/README.rst
examples/barbecue/dist/barbecue-0.1b1/setup.cfg
examples/barbecue/dist/barbecue-0.1b1/setup.py
examples/barbecue/dist/barbecue-0.1b1/barbecue/__init__.py
examples/barbecue/dist/barbecue-0.1b1/barbecue/_barbecue.py
examples/barbecue/dist/barbecue-0.1b1/barbecue/schema/barbecue-time.yml
examples/barbecue/dist/barbecue-0.1b1/bin/barbecue-time
examples/barbecue/test-data/time-config.yml
html/genindex.html
html/index.html
html/intro.html
html/objects.inv
html/phyles-api.html
html/py-modindex.html
html/search.html
html/searchindex.js
html/tutorial.html
html/_images/math/213cc44f2354247a15d1aa5b0545b798f48160c8.png
html/_images/math/2fdf98e64c82a62b9ccb344b191078d0d28d2c48.png
html/_images/math/49c0f61e8e09bf51d0f3b59ca429feb72f22d9ee.png
html/_images/math/5423068b59cb0d35252c5504906bac2e650aa964.png
html/_images/math/9102baec19532baea5ebf4c6a374a03b013b74d0.png
html/_sources/index.txt
html/_sources/intro.txt
html/_sources/phyles-api.txt
html/_sources/tutorial.txt
html/_static/ajax-loader.gif
html/_static/basic.css
html/_static/comment-bright.png
html/_static/comment-close.png
html/_static/comment.png
html/_static/default.css
html/_static/doctools.js
html/_static/down-pressed.png
html/_static/down.png
html/_static/file.png
html/_static/jquery.js
phyles.egg-info/PKG-INFO
phyles.egg-info/SOURCES.txt
phyles.egg-info/dependency_links.txt
phyles.egg-info/entry_points.txt
phyles.egg-info/requires.txt
phyles.egg-info/top_level.txt
