Metadata-Version: 1.1
Name: phyles
Version: 0.2.16
Summary: Simple validation of YAML config files with YAML-based schema.
Home-page: http://phyles.bravais.net
Author: James C. Stroud
Author-email: jstroud@mbi.ucla.edu
License: BSD
Platform: UNKNOWN
Classifier: Programming Language :: Python :: 2.6
Classifier: Programming Language :: Python :: 2.7
